airflow_socrata/__init__.py
airflow_socrata/socrata_plugin.py
airflow_socrata/hooks/__init__.py
airflow_socrata/hooks/socrata_hook.py
airflow_socrata/operators/__init__.py
airflow_socrata/operators/socrata_operator.py
airflow_socrata_plugin-0.0.1.dist-info/LICENSE
airflow_socrata_plugin-0.0.1.dist-info/METADATA
airflow_socrata_plugin-0.0.1.dist-info/WHEEL
airflow_socrata_plugin-0.0.1.dist-info/entry_points.txt
airflow_socrata_plugin-0.0.1.dist-info/top_level.txt
airflow_socrata_plugin-0.0.1.dist-info/RECORD
