Metadata-Version: 2.1
Name: airflow-socrata-plugin
Version: 0.0.1
Summary: An Apache Airflow plugin to upload to Socrata.
Home-page: https://github.com/xyx0826/Airflow-Socrata
Author: xyx0826
Author-email: xyx0826@hotmail.com
License: UNKNOWN
Platform: UNKNOWN
Classifier: Programming Language :: Python :: 3
Classifier: License :: OSI Approved :: MIT License
Classifier: Operating System :: POSIX :: Linux
Classifier: Environment :: Plugins
